<persistence xmlns="http://java.sun.com/xml/ns/persistence"
		xmlns:xsi="http://www.w3.org/2001/XMLSchema-instance"
		xsi:schemaLocation="http://java.sun.com/xml/ns/persistence http://java.sun.com/xml/ns/persistence/persistence_1_0.xsd"
		version="1.0">

	<persistence-unit name="mxheroPer" transaction-type="RESOURCE_LOCAL">
		<provider>org.hibernate.ejb.HibernatePersistence</provider>
		<class>org.mxhero.engine.plugin.dbfinder.internal.entity.DBAliasAccount</class> 
		<class>org.mxhero.engine.plugin.dbfinder.internal.entity.DBAliasAccountPk</class>
		<class>org.mxhero.engine.plugin.dbfinder.internal.entity.DBDomain</class> 
		<class>org.mxhero.engine.plugin.dbfinder.internal.entity.DBDomainAlias</class>	
		<class>org.mxhero.engine.plugin.dbfinder.internal.entity.DBEmailAccount</class>	
		<class>org.mxhero.engine.plugin.dbfinder.internal.entity.DBEmailAccountPk</class>	
		<exclude-unlisted-classes/>
	</persistence-unit>

</persistence>