<?xml version="1.0" encoding="UTF-8"?>
<beans xmlns="http://www.springframework.org/schema/beans"
	xmlns:xsi="http://www.w3.org/2001/XMLSchema-instance" 
	xmlns:aop="http://www.springframework.org/schema/aop"
	xmlns:context="http://www.springframework.org/schema/context"
	xmlns:osgi="http://www.springframework.org/schema/osgi"
	xmlns:osgix="http://www.springframework.org/schema/osgi-compendium"
	xsi:schemaLocation="http://www.springframework.org/schema/beans http://www.springframework.org/schema/beans/spring-beans-3.0.xsd
		http://www.springframework.org/schema/aop http://www.springframework.org/schema/aop/spring-aop-3.0.xsd
		http://www.springframework.org/schema/context http://www.springframework.org/schema/context/spring-context-3.0.xsd
		http://www.springframework.org/schema/osgi http://www.springframework.org/schema/osgi/spring-osgi.xsd
		http://www.springframework.org/schema/osgi-compendium http://www.springframework.org/schema/osgi-compendium/spring-osgi-compendium.xsd">

	<osgix:cm-properties id="cmProps"
		persistent-id="org.mxhero.engine.fsqueues">
		<prop key="capacity">1000</prop>
		<prop key="deferredSize">1048576</prop>
		<prop key="storePrefix">store</prop>
		<prop key="tmpPrefix">tmp</prop>
		<prop key="suffix">.eml</prop>
		<prop key="storePath">/opt/mxhero/fsqueue</prop>
		<prop key="loadPath">/opt/mxhero/fsloader</prop>
		<prop key="tmpPath">/tmp</prop>
	</osgix:cm-properties>

	<context:property-placeholder
		properties-ref="cmProps" />

	<context:component-scan base-package="org.mxhero.engine.fsqueues" />

	<context:annotation-config />

	<osgi:service ref="queueService">
	  	<osgi:interfaces>
	  		<value>org.mxhero.engine.commons.queue.MimeMailQueueService</value>
	  	</osgi:interfaces>
	  	<osgi:service-properties>
     		<entry key="service.pid" value="org.mxhero.engine.fsqueues.internal.FSQueueService"/>
   		</osgi:service-properties>
	</osgi:service>

	<bean id="queueService" class="org.mxhero.engine.fsqueues.internal.FSQueueService" 
		init-method="init"
		destroy-method="stop">
		<constructor-arg  ref="config"/>
	</bean>

	<bean id="config" class="org.mxhero.engine.fsqueues.internal.FSConfig">
		<osgix:managed-properties persistent-id="org.mxhero.engine.fsqueues" update-strategy="container-managed"/>
		<constructor-arg  value="${storePath}"/>
		<constructor-arg  value="${tmpPath}"/>
	</bean>
	
	<bean id="loader" class="org.mxhero.engine.fsqueues.internal.loader.FSLoader"
		init-method="init"
		destroy-method="stop">
		<constructor-arg  value="${loadPath}"/>
		<constructor-arg  value="${tmpPath}"/>
		<property name="queueService" ref="queueService"/>
	</bean>
</beans>
